LICENSE
README.md
setup.py
pidpromptify.egg-info/PKG-INFO
pidpromptify.egg-info/SOURCES.txt
pidpromptify.egg-info/dependency_links.txt
pidpromptify.egg-info/requires.txt
pidpromptify.egg-info/top_level.txt
promptify/__init__.py
promptify/data/__init__.py
promptify/embeddings/__init__.py
promptify/models/__init__.py
promptify/models/nlp/__init__.py
promptify/models/nlp/hub_model.py
promptify/models/nlp/model.py
promptify/models/nlp/openai_model.py
promptify/models/nlp/utils/__init__.py
promptify/models/nlp/utils/bpe_encoder.py
promptify/models/nlp/utils/utils.py
promptify/models/tabular/__init__.py
promptify/models/vision/__init__.py
promptify/parser/__init__.py
promptify/parser/parser.py
promptify/pipelines/__init__.py
promptify/plugins/__init__.py
promptify/prompter/__init__.py
promptify/prompts/__init__.py
promptify/prompts/nlp/__init__.py
promptify/prompts/nlp/prompter.py
promptify/prompts/nlp/templates/JD.jinja
promptify/prompts/nlp/templates/__init__.py
promptify/prompts/nlp/templates/binary_classification.jinja
promptify/prompts/nlp/templates/explain.jinja
promptify/prompts/nlp/templates/gen_data.jinja
promptify/prompts/nlp/templates/multiclass_classification.jinja
promptify/prompts/nlp/templates/multilabel_classification.jinja
promptify/prompts/nlp/templates/ner.jinja
promptify/prompts/nlp/templates/pickdeal.jinja
promptify/prompts/nlp/templates/qa.jinja
promptify/prompts/nlp/templates/qa_gen.jinja
promptify/prompts/nlp/templates/relation_extraction.jinja
promptify/prompts/nlp/templates/sql_writer.jinja
promptify/prompts/nlp/templates/summary.jinja
promptify/prompts/nlp/templates/tabular_extractor.jinja
promptify/prompts/tabular/__init__.py
promptify/prompts/vision/__init__.py
promptify/utils/__init__.py
tests/__init__.py
tests/unit_tests/__init__.py
tests/unit_tests/models/__init__.py
tests/unit_tests/models/test_base_model.py
tests/unit_tests/models/test_hf_model.py
tests/unit_tests/models/test_openai_model.py
tests/unit_tests/parser/__init__.py
tests/unit_tests/parser/test_parser.py
tests/unit_tests/prompter/__init__.py
utils/__init__.py
utils/pickdeal.py