Metadata-Version: 2.1
Name: pidpromptify
Version: 0.2
Summary: Use GPT or other prompt based models to get structured output
Home-page: https://github.com/NguyenThaiHoc1/PD_Promotify
Author: NTH
Maintainer: The promptslab team with the help of all our contributors
License: Apache
Requires-Python: >=3.7.0
License-File: LICENSE
